jupyter_activity_monitor_extension/__init__.py
jupyter_activity_monitor_extension/docker_sidecar_check.py
jupyter_activity_monitor_extension/handler.py
jupyter_activity_monitor_extension/idle_status_detector.py
jupyter_activity_monitor_extension/tests/__init__.py
jupyter_activity_monitor_extension/tests/test_handlers.py
jupyter_activity_monitor_extension/tests/test_idle_status_detector.py
jupyter_activity_monitor_extension/tests/test_sidecar_check.py
jupyter_activity_monitor_extension-0.3.2.data/data/etc/jupyter/jupyter_server_config.d/jupyter_activity_monitor_extension.json
jupyter_activity_monitor_extension-0.3.2.dist-info/licenses/LICENSE
jupyter_activity_monitor_extension-0.3.2.dist-info/METADATA
jupyter_activity_monitor_extension-0.3.2.dist-info/WHEEL
jupyter_activity_monitor_extension-0.3.2.dist-info/top_level.txt
jupyter_activity_monitor_extension-0.3.2.dist-info/RECORD
